cvedb2/__init__.py
cvedb2/__main__.py
cvedb2/cli.py
cvedb2/cpe.py
cvedb2/cve.py
cvedb2/db.py
cvedb2/feed.py
cvedb2/nvd.py
cvedb2/printing.py
cvedb2/schemas.py
cvedb2/search.py
cvedb2/sql.py
cvedb2-1.0.1.dist-info/licenses/LICENSE
cvedb2-1.0.1.dist-info/METADATA
cvedb2-1.0.1.dist-info/WHEEL
cvedb2-1.0.1.dist-info/entry_points.txt
cvedb2-1.0.1.dist-info/top_level.txt
cvedb2-1.0.1.dist-info/RECORD
