Metadata-Version: 2.4
Name: cvedb2
Version: 1.0.1
Summary: Yet another CVE database
Home-page: https://github.com/ahntenna/cvedb2
Author: ahntenna
License: LGPL-3.0-or-later
Classifier: Development Status :: 4 - Beta
Classifier: Environment :: Console
Classifier: Intended Audience :: Science/Research
Classifier: License :: OSI Approved :: GNU Lesser General Public License v3 or later (LGPLv3+)
Classifier: Programming Language :: Python :: 3 :: Only
Classifier: Topic :: Utilities
Requires-Python: >=3.6
License-File: LICENSE
Requires-Dist: cvss>=3.6
Requires-Dist: dataclasses; python_version < "3.7"
Requires-Dist: python-dateutil>=2.8.1
Requires-Dist: tqdm==4.66.3
Provides-Extra: dev
Requires-Dist: flake8; extra == "dev"
Requires-Dist: pytest; extra == "dev"
Requires-Dist: rstr~=2.2.6; extra == "dev"
Requires-Dist: twine; extra == "dev"
Dynamic: author
Dynamic: classifier
Dynamic: description
Dynamic: description-content-type
Dynamic: home-page
Dynamic: license
Dynamic: license-file
Dynamic: provides-extra
Dynamic: requires-dist
Dynamic: requires-python
Dynamic: summary
